nonebot_plugin_skills/__init__.py
nonebot_plugin_skills/config.py
nonebot_plugin_skills-0.1.2.dist-info/METADATA
nonebot_plugin_skills-0.1.2.dist-info/WHEEL
nonebot_plugin_skills-0.1.2.dist-info/licenses/LICENSE
nonebot_plugin_skills-0.1.2.dist-info/RECORD
