Metadata-Version: 2.4
Name: nonebot-plugin-skills
Version: 0.1.2
Summary: Gemini avatar/image and chat plugin with skills and context cache for NoneBot2
License-File: LICENSE
Author: yourname
Author-email: you@example.com
Requires-Python: >=3.9
Classifier: Programming Language :: Python :: 3
Classifier: Programming Language :: Python :: 3.9
Classifier: Programming Language :: Python :: 3.10
Classifier: Programming Language :: Python :: 3.11
Classifier: Programming Language :: Python :: 3.12
Classifier: Programming Language :: Python :: 3.13
Classifier: Programming Language :: Python :: 3.14
Requires-Dist: google-genai (>=1.0.0)
Requires-Dist: httpx (>=0.24.0)
Requires-Dist: nonebot-adapter-onebot (>=2.2.0)
Requires-Dist: nonebot2 (>=2.2.0)
Requires-Dist: pydantic (>=1.10)
